LICENSE
MANIFEST.in
README.md
requirements.txt
setup.py
test_requirements.txt
Reding.egg-info/PKG-INFO
Reding.egg-info/SOURCES.txt
Reding.egg-info/dependency_links.txt
Reding.egg-info/requires.txt
Reding.egg-info/top_level.txt
reding/__init__.py
reding/app.py
reding/managers.py
reding/resources.py
reding/settings.py
reding/tests/__init__.py
reding/tests/documentation.py
reding/tests/generics.py
reding/tests/utils.py