Metadata-Version: 1.1
Name: Reding
Version: 1.99.1
Summary: [![PyPi downloads](https://pypip.in/d/Reding/badge.png)](https://crate.io/packages/Reding/)
